[
    {
        "delta": 0.01, 
        "epsilon": 7.0, 
        "matrix": "3dtube_conv", 
        "matrix_domain": "Computational Fluid Dynamics", 
        "matrix_m": 45330, 
        "matrix_n": 45330, 
        "matrix_name": "3dtube", 
        "matrix_nnz": 3213618, 
        "matrix_size": 43480516, 
        "normal_spmv_time": 0.00069365978240966799, 
        "oski_mean_max_error": 0.38206310966166479, 
        "oski_mean_spmv_time": 0.00047406878471374474, 
        "oski_mean_time": 0.00614950087890625, 
        "oski_std_max_error": 0.17588810315179357, 
        "phil_mean_max_error": 0.42828321768166511, 
        "phil_mean_spmv_time": 0.00039956667423248242, 
        "phil_mean_time": 0.00022563096862793008, 
        "phil_std_max_error": 0.1534432235168014, 
        "sigma": 0.001
    }, 
    {
        "delta": 0.01, 
        "epsilon": 4.932880780615621, 
        "matrix": "3dtube_conv", 
        "matrix_domain": "Computational Fluid Dynamics", 
        "matrix_m": 45330, 
        "matrix_n": 45330, 
        "matrix_name": "3dtube", 
        "matrix_nnz": 3213618, 
        "matrix_size": 43480516, 
        "normal_spmv_time": 0.00069365978240966799, 
        "oski_mean_max_error": 0.28585114411811047, 
        "oski_mean_spmv_time": 0.0004114982604980462, 
        "oski_mean_time": 0.008237499571533203, 
        "oski_std_max_error": 0.12924640479559399, 
        "phil_mean_max_error": 0.30711105693596097, 
        "phil_mean_spmv_time": 0.00039918355941772412, 
        "phil_mean_time": 0.00026921949905395535, 
        "phil_std_max_error": 0.12022608025393018, 
        "sigma": 0.0015066301902946675
    }, 
    {
        "delta": 0.01, 
        "epsilon": 3.4761875422524255, 
        "matrix": "3dtube_conv", 
        "matrix_domain": "Computational Fluid Dynamics", 
        "matrix_m": 45330, 
        "matrix_n": 45330, 
        "matrix_name": "3dtube", 
        "matrix_nnz": 3213618, 
        "matrix_size": 43480516, 
        "normal_spmv_time": 0.00069365978240966799, 
        "oski_mean_max_error": 0.21420427095006966, 
        "oski_mean_spmv_time": 0.0003962126731872554, 
        "oski_mean_time": 0.011172099959564207, 
        "oski_std_max_error": 0.086620930519429193, 
        "phil_mean_max_error": 0.19487879664099222, 
        "phil_mean_spmv_time": 0.00039783315658569287, 
        "phil_mean_time": 0.0008886091123962403, 
        "phil_std_max_error": 0.056400838804867806, 
        "sigma": 0.002269934530307346
    }, 
    {
        "delta": 0.01, 
        "epsilon": 2.449659816713206, 
        "matrix": "3dtube_conv", 
        "matrix_domain": "Computational Fluid Dynamics", 
        "matrix_m": 45330, 
        "matrix_n": 45330, 
        "matrix_name": "3dtube", 
        "matrix_nnz": 3213618, 
        "matrix_size": 43480516, 
        "normal_spmv_time": 0.00069365978240966799, 
        "oski_mean_max_error": 0.17084525135032524, 
        "oski_mean_spmv_time": 0.00039567251205444292, 
        "oski_mean_time": 0.02059663995376587, 
        "oski_std_max_error": 0.059721426386754532, 
        "phil_mean_max_error": 0.14688166846751669, 
        "phil_mean_spmv_time": 0.00040107412338256828, 
        "phil_mean_time": 0.001163110406494141, 
        "phil_std_max_error": 0.044151593556686179, 
        "sigma": 0.0034199518933533935
    }, 
    {
        "delta": 0.01, 
        "epsilon": 1.7262685469872798, 
        "matrix": "3dtube_conv", 
        "matrix_domain": "Computational Fluid Dynamics", 
        "matrix_m": 45330, 
        "matrix_n": 45330, 
        "matrix_name": "3dtube", 
        "matrix_nnz": 3213618, 
        "matrix_size": 43480516, 
        "normal_spmv_time": 0.00069365978240966799, 
        "oski_mean_max_error": 0.13825728827718314, 
        "oski_mean_spmv_time": 0.00039378194808959897, 
        "oski_mean_time": 0.02248235066040039, 
        "oski_std_max_error": 0.054692203621003015, 
        "phil_mean_max_error": 0.10035835370903654, 
        "phil_mean_spmv_time": 0.00039756307601928676, 
        "phil_mean_time": 0.0023894294132995606, 
        "phil_std_max_error": 0.027274592929901378, 
        "sigma": 0.005152602771881632
    }, 
    {
        "delta": 0.01, 
        "epsilon": 1.2164967053735438, 
        "matrix": "3dtube_conv", 
        "matrix_domain": "Computational Fluid Dynamics", 
        "matrix_m": 45330, 
        "matrix_n": 45330, 
        "matrix_name": "3dtube", 
        "matrix_nnz": 3213618, 
        "matrix_size": 43480516, 
        "normal_spmv_time": 0.00069365978240966799, 
        "oski_mean_max_error": 0.11208372866347399, 
        "oski_mean_spmv_time": 0.00039432210922241162, 
        "oski_mean_time": 0.03500969089050293, 
        "oski_std_max_error": 0.038962259746949127, 
        "phil_mean_max_error": 0.071326345092807372, 
        "phil_mean_spmv_time": 0.00039486227035522416, 
        "phil_mean_time": 0.004642529285736084, 
        "phil_std_max_error": 0.017543602437922322, 
        "sigma": 0.007763066894712853
    }, 
    {
        "delta": 0.01, 
        "epsilon": 0.8572618882313398, 
        "matrix": "3dtube_conv", 
        "matrix_domain": "Computational Fluid Dynamics", 
        "matrix_m": 45330, 
        "matrix_n": 45330, 
        "matrix_name": "3dtube", 
        "matrix_nnz": 3213618, 
        "matrix_size": 43480516, 
        "normal_spmv_time": 0.00069365978240966799, 
        "oski_mean_max_error": 0.095345872720080424, 
        "oski_mean_spmv_time": 0.00039324178695678664, 
        "oski_mean_time": 0.04984908116622924, 
        "oski_std_max_error": 0.034413948686034548, 
        "phil_mean_max_error": 0.051461457898187207, 
        "phil_mean_spmv_time": 0.0003935118675231928, 
        "phil_mean_time": 0.011466209967498779, 
        "phil_std_max_error": 0.012816787843962847, 
        "sigma": 0.01169607095285146
    }, 
    {
        "delta": 0.01, 
        "epsilon": 0.6041100989158047, 
        "matrix": "3dtube_conv", 
        "matrix_domain": "Computational Fluid Dynamics", 
        "matrix_m": 45330, 
        "matrix_n": 45330, 
        "matrix_name": "3dtube", 
        "matrix_nnz": 3213618, 
        "matrix_size": 43480516, 
        "normal_spmv_time": 0.00069365978240966799, 
        "oski_mean_max_error": 0.079716733863212597, 
        "oski_mean_spmv_time": 0.00039270162582397399, 
        "oski_mean_time": 0.07453118068588256, 
        "oski_std_max_error": 0.032070135285894787, 
        "phil_mean_max_error": 0.035599060773265558, 
        "phil_mean_spmv_time": 0.00039270162582397399, 
        "phil_mean_time": 0.018228910886383058, 
        "phil_std_max_error": 0.0094123102004593541, 
        "sigma": 0.017621653605394527
    }, 
    {
        "delta": 0.01, 
        "epsilon": 0.4257147280453678, 
        "matrix": "3dtube_conv", 
        "matrix_domain": "Computational Fluid Dynamics", 
        "matrix_m": 45330, 
        "matrix_n": 45330, 
        "matrix_name": "3dtube", 
        "matrix_nnz": 3213618, 
        "matrix_size": 43480516, 
        "normal_spmv_time": 0.00069365978240966799, 
        "oski_mean_max_error": 0.06067970898881607, 
        "oski_mean_spmv_time": 0.00039270162582397399, 
        "oski_mean_time": 0.11190819915847779, 
        "oski_std_max_error": 0.020978333898464162, 
        "phil_mean_max_error": 0.024163463375010248, 
        "phil_mean_spmv_time": 0.00039270162582397399, 
        "phil_mean_time": 0.03802761015777588, 
        "phil_std_max_error": 0.0055799419755615878, 
        "sigma": 0.026549315324802272
    }, 
    {
        "delta": 0.01, 
        "epsilon": 0.3000000000000001, 
        "matrix": "3dtube_conv", 
        "matrix_domain": "Computational Fluid Dynamics", 
        "matrix_m": 45330, 
        "matrix_n": 45330, 
        "matrix_name": "3dtube", 
        "matrix_nnz": 3213618, 
        "matrix_size": 43480516, 
        "normal_spmv_time": 0.00069365978240966799, 
        "oski_mean_max_error": 0.049732051533081127, 
        "oski_mean_spmv_time": 0.00039270162582397399, 
        "oski_mean_time": 0.16646274978820802, 
        "oski_std_max_error": 0.015285548514866142, 
        "phil_mean_max_error": 0.017477650649432307, 
        "phil_mean_spmv_time": 0.00039270162582397399, 
        "phil_mean_time": 0.08397624031677246, 
        "phil_std_max_error": 0.0045146809919516476, 
        "sigma": 0.03999999999999998
    }
]