[
    {
        "delta": 0.01, 
        "epsilon": 2.0, 
        "matrix": "pathological_phil", 
        "matrix_domain": "Synthetic", 
        "matrix_m": 11989, 
        "matrix_n": 12000, 
        "matrix_name": "pathological_PHIL", 
        "matrix_nnz": 72356, 
        "matrix_size": 2326231, 
        "normal_spmv_time": 4.021167755126953e-05, 
        "oski_mean_max_error": 2.1403763485325937, 
        "oski_mean_spmv_time": 5.159900188446036e-05, 
        "oski_mean_time": 0.0016576190325927737, 
        "oski_std_max_error": 9.9212369633591049, 
        "phil_mean_max_error": 0.21922012478747374, 
        "phil_mean_spmv_time": 5.1629543304443267e-05, 
        "phil_mean_time": 0.0014151005487060546, 
        "phil_std_max_error": 0.14047646844262968, 
        "sigma": 0.01
    }, 
    {
        "delta": 0.01, 
        "epsilon": 1.619886477429669, 
        "matrix": "pathological_phil", 
        "matrix_domain": "Synthetic", 
        "matrix_m": 11989, 
        "matrix_n": 12000, 
        "matrix_name": "pathological_PHIL", 
        "matrix_nnz": 72356, 
        "matrix_size": 2326231, 
        "normal_spmv_time": 4.021167755126953e-05, 
        "oski_mean_max_error": 0.41444082714065777, 
        "oski_mean_spmv_time": 5.1524686813354409e-05, 
        "oski_mean_time": 0.0021408103067016605, 
        "oski_std_max_error": 0.24096076332968147, 
        "phil_mean_max_error": 0.17104942881424059, 
        "phil_mean_spmv_time": 5.1629543304443267e-05, 
        "phil_mean_time": 0.0021514708651733405, 
        "phil_std_max_error": 0.11835581879824607, 
        "sigma": 0.01668100537200059
    }, 
    {
        "delta": 0.01, 
        "epsilon": 1.312016099879751, 
        "matrix": "pathological_phil", 
        "matrix_domain": "Synthetic", 
        "matrix_m": 11989, 
        "matrix_n": 12000, 
        "matrix_name": "pathological_PHIL", 
        "matrix_nnz": 72356, 
        "matrix_size": 2326231, 
        "normal_spmv_time": 4.021167755126953e-05, 
        "oski_mean_max_error": 0.31759802332434611, 
        "oski_mean_spmv_time": 5.1585769653320224e-05, 
        "oski_mean_time": 0.0025296503315734866, 
        "oski_std_max_error": 0.16145406725418851, 
        "phil_mean_max_error": 0.15695859429176237, 
        "phil_mean_spmv_time": 5.1629543304443267e-05, 
        "phil_mean_time": 0.002484308949890137, 
        "phil_std_max_error": 0.10546724652714365, 
        "sigma": 0.02782559402207125
    }, 
    {
        "delta": 0.01, 
        "epsilon": 1.0626585691826111, 
        "matrix": "pathological_phil", 
        "matrix_domain": "Synthetic", 
        "matrix_m": 11989, 
        "matrix_n": 12000, 
        "matrix_name": "pathological_PHIL", 
        "matrix_nnz": 72356, 
        "matrix_size": 2326231, 
        "normal_spmv_time": 4.021167755126953e-05, 
        "oski_mean_max_error": 0.2074239938142412, 
        "oski_mean_spmv_time": 5.160164833068838e-05, 
        "oski_mean_time": 0.0037591407389831544, 
        "oski_std_max_error": 0.074968136741046743, 
        "phil_mean_max_error": 0.11522324327308993, 
        "phil_mean_spmv_time": 5.1629543304443267e-05, 
        "phil_mean_time": 0.0037985992239379885, 
        "phil_std_max_error": 0.079553550052775895, 
        "sigma": 0.046415888336127795
    }, 
    {
        "delta": 0.01, 
        "epsilon": 0.8606931231718362, 
        "matrix": "pathological_phil", 
        "matrix_domain": "Synthetic", 
        "matrix_m": 11989, 
        "matrix_n": 12000, 
        "matrix_name": "pathological_PHIL", 
        "matrix_nnz": 72356, 
        "matrix_size": 2326231, 
        "normal_spmv_time": 4.021167755126953e-05, 
        "oski_mean_max_error": 0.17162525410035406, 
        "oski_mean_spmv_time": 5.1629543304443267e-05, 
        "oski_mean_time": 0.005979260540924072, 
        "oski_std_max_error": 0.076275556666302216, 
        "phil_mean_max_error": 0.099123872276732583, 
        "phil_mean_spmv_time": 5.1629543304443267e-05, 
        "phil_mean_time": 0.005748230587463379, 
        "phil_std_max_error": 0.06173900616149914, 
        "sigma": 0.07742636826811271
    }, 
    {
        "delta": 0.01, 
        "epsilon": 0.6971125757213831, 
        "matrix": "pathological_phil", 
        "matrix_domain": "Synthetic", 
        "matrix_m": 11989, 
        "matrix_n": 12000, 
        "matrix_name": "pathological_PHIL", 
        "matrix_nnz": 72356, 
        "matrix_size": 2326231, 
        "normal_spmv_time": 4.021167755126953e-05, 
        "oski_mean_max_error": 0.12012060461574342, 
        "oski_mean_spmv_time": 5.1629543304443267e-05, 
        "oski_mean_time": 0.009642970784454346, 
        "oski_std_max_error": 0.045406368058426634, 
        "phil_mean_max_error": 0.073505006378723065, 
        "phil_mean_spmv_time": 5.1629543304443267e-05, 
        "phil_mean_time": 0.008747709042358397, 
        "phil_std_max_error": 0.046829281491906356, 
        "sigma": 0.12915496650148842
    }, 
    {
        "delta": 0.01, 
        "epsilon": 0.5646216173286173, 
        "matrix": "pathological_phil", 
        "matrix_domain": "Synthetic", 
        "matrix_m": 11989, 
        "matrix_n": 12000, 
        "matrix_name": "pathological_PHIL", 
        "matrix_nnz": 72356, 
        "matrix_size": 2326231, 
        "normal_spmv_time": 4.021167755126953e-05, 
        "oski_mean_max_error": 0.088290662899446218, 
        "oski_mean_spmv_time": 5.1629543304443267e-05, 
        "oski_mean_time": 0.01588226117401123, 
        "oski_std_max_error": 0.032184976409414562, 
        "phil_mean_max_error": 0.0604207300467801, 
        "phil_mean_spmv_time": 5.1629543304443267e-05, 
        "phil_mean_time": 0.0133494397265625, 
        "phil_std_max_error": 0.043051301341361432, 
        "sigma": 0.2154434690031884
    }, 
    {
        "delta": 0.01, 
        "epsilon": 0.45731146138754825, 
        "matrix": "pathological_phil", 
        "matrix_domain": "Synthetic", 
        "matrix_m": 11989, 
        "matrix_n": 12000, 
        "matrix_name": "pathological_PHIL", 
        "matrix_nnz": 72356, 
        "matrix_size": 2326231, 
        "normal_spmv_time": 4.021167755126953e-05, 
        "oski_mean_max_error": 0.058779276991423386, 
        "oski_mean_spmv_time": 5.1629543304443267e-05, 
        "oski_mean_time": 0.025805748844604494, 
        "oski_std_max_error": 0.018349026044621089, 
        "phil_mean_max_error": 0.045598899030714263, 
        "phil_mean_spmv_time": 5.1629543304443267e-05, 
        "phil_mean_time": 0.02029104032699585, 
        "phil_std_max_error": 0.031590100670238506, 
        "sigma": 0.3593813663804628
    }, 
    {
        "delta": 0.01, 
        "epsilon": 0.37039632613764484, 
        "matrix": "pathological_phil", 
        "matrix_domain": "Synthetic", 
        "matrix_m": 11989, 
        "matrix_n": 12000, 
        "matrix_name": "pathological_PHIL", 
        "matrix_nnz": 72356, 
        "matrix_size": 2326231, 
        "normal_spmv_time": 4.021167755126953e-05, 
        "oski_mean_max_error": 0.037786470156278826, 
        "oski_mean_spmv_time": 5.1629543304443267e-05, 
        "oski_mean_time": 0.04232763970199585, 
        "oski_std_max_error": 0.013044069063572857, 
        "phil_mean_max_error": 0.044294789527508156, 
        "phil_mean_spmv_time": 5.1629543304443267e-05, 
        "phil_mean_time": 0.030919300281219485, 
        "phil_std_max_error": 0.028921593972368775, 
        "sigma": 0.5994842503189411
    }, 
    {
        "delta": 0.01, 
        "epsilon": 0.30000000000000016, 
        "matrix": "pathological_phil", 
        "matrix_domain": "Synthetic", 
        "matrix_m": 11989, 
        "matrix_n": 12000, 
        "matrix_name": "pathological_PHIL", 
        "matrix_nnz": 72356, 
        "matrix_size": 2326231, 
        "normal_spmv_time": 4.021167755126953e-05, 
        "oski_mean_max_error": 0.0029875936587784131, 
        "oski_mean_spmv_time": 5.1629543304443267e-05, 
        "oski_mean_time": 0.06926916108398437, 
        "oski_std_max_error": 4.3368086899420177e-19, 
        "phil_mean_max_error": 0.03466640426553097, 
        "phil_mean_spmv_time": 5.1629543304443267e-05, 
        "phil_mean_time": 0.047091549267730716, 
        "phil_std_max_error": 0.023639941308780683, 
        "sigma": 1.0000000000000002
    }
]