[
    {
        "delta": 0.01, 
        "epsilon": 2.0, 
        "matrix": "pathological_oski", 
        "matrix_domain": "Synthetic", 
        "matrix_m": 100000, 
        "matrix_n": 100000, 
        "matrix_name": "pathological_OSKI", 
        "matrix_nnz": 699994, 
        "matrix_size": 6922298, 
        "normal_spmv_time": 0.0011512398719787597, 
        "oski_mean_max_error": 3.6666882669600089, 
        "oski_mean_spmv_time": 0.00073086023330688613, 
        "oski_mean_time": 0.010708579794921876, 
        "oski_std_max_error": 6.1910624235256996e-06, 
        "phil_mean_max_error": 0.06086612003928079, 
        "phil_mean_spmv_time": 0.0007305097579956058, 
        "phil_mean_time": 0.0013679490974426278, 
        "phil_std_max_error": 0.031729303304624604, 
        "sigma": 0.01
    }, 
    {
        "delta": 0.01, 
        "epsilon": 1.619886477429669, 
        "matrix": "pathological_oski", 
        "matrix_domain": "Synthetic", 
        "matrix_m": 100000, 
        "matrix_n": 100000, 
        "matrix_name": "pathological_OSKI", 
        "matrix_nnz": 699994, 
        "matrix_size": 6922298, 
        "normal_spmv_time": 0.0011512398719787597, 
        "oski_mean_max_error": 3.6666882669600089, 
        "oski_mean_spmv_time": 0.0007308567285537733, 
        "oski_mean_time": 0.012821670081939698, 
        "oski_std_max_error": 6.1910624235265924e-06, 
        "phil_mean_max_error": 0.049663331532117549, 
        "phil_mean_spmv_time": 0.0007305097579956058, 
        "phil_mean_time": 0.001801610682678223, 
        "phil_std_max_error": 0.025944857381226327, 
        "sigma": 0.01668100537200059
    }, 
    {
        "delta": 0.01, 
        "epsilon": 1.312016099879751, 
        "matrix": "pathological_oski", 
        "matrix_domain": "Synthetic", 
        "matrix_m": 100000, 
        "matrix_n": 100000, 
        "matrix_name": "pathological_OSKI", 
        "matrix_nnz": 699994, 
        "matrix_size": 6922298, 
        "normal_spmv_time": 0.0011512398719787597, 
        "oski_mean_max_error": 3.6666864002844535, 
        "oski_mean_spmv_time": 0.00073085322380066057, 
        "oski_mean_time": 0.023699828859405518, 
        "oski_std_max_error": 1.2193073671194548e-05, 
        "phil_mean_max_error": 0.037464904817636813, 
        "phil_mean_spmv_time": 0.0007305097579956058, 
        "phil_mean_time": 0.0027175909732055662, 
        "phil_std_max_error": 0.019263439206205376, 
        "sigma": 0.02782559402207125
    }, 
    {
        "delta": 0.01, 
        "epsilon": 1.0626585691826111, 
        "matrix": "pathological_oski", 
        "matrix_domain": "Synthetic", 
        "matrix_m": 100000, 
        "matrix_n": 100000, 
        "matrix_name": "pathological_OSKI", 
        "matrix_nnz": 699994, 
        "matrix_size": 6922298, 
        "normal_spmv_time": 0.0011512398719787597, 
        "oski_mean_max_error": 3.6666870225096386, 
        "oski_mean_spmv_time": 0.00073083920478820923, 
        "oski_mean_time": 0.03477908960067749, 
        "oski_std_max_error": 1.0614366524149707e-05, 
        "phil_mean_max_error": 0.031009321923093847, 
        "phil_mean_spmv_time": 0.0007305097579956058, 
        "phil_mean_time": 0.004122830761871338, 
        "phil_std_max_error": 0.018565711178951422, 
        "sigma": 0.046415888336127795
    }, 
    {
        "delta": 0.01, 
        "epsilon": 0.8606931231718362, 
        "matrix": "pathological_oski", 
        "matrix_domain": "Synthetic", 
        "matrix_m": 100000, 
        "matrix_n": 100000, 
        "matrix_name": "pathological_OSKI", 
        "matrix_nnz": 699994, 
        "matrix_size": 6922298, 
        "normal_spmv_time": 0.0011512398719787597, 
        "oski_mean_max_error": 3.6666820447081561, 
        "oski_mean_spmv_time": 0.00073082518577575822, 
        "oski_mean_time": 0.0568081708670044, 
        "oski_std_max_error": 1.9468788696879355e-05, 
        "phil_mean_max_error": 0.029054735445145495, 
        "phil_mean_spmv_time": 0.0007305097579956058, 
        "phil_mean_time": 0.006159479337158203, 
        "phil_std_max_error": 0.014841413429090979, 
        "sigma": 0.07742636826811271
    }, 
    {
        "delta": 0.01, 
        "epsilon": 0.6971125757213831, 
        "matrix": "pathological_oski", 
        "matrix_domain": "Synthetic", 
        "matrix_m": 100000, 
        "matrix_n": 100000, 
        "matrix_name": "pathological_OSKI", 
        "matrix_nnz": 699994, 
        "matrix_size": 6922298, 
        "normal_spmv_time": 0.0011512398719787597, 
        "oski_mean_max_error": 3.6666752002311194, 
        "oski_mean_spmv_time": 0.00073079714775085565, 
        "oski_mean_time": 0.10497297977401733, 
        "oski_std_max_error": 2.5775448295020798e-05, 
        "phil_mean_max_error": 0.021201155115095235, 
        "phil_mean_spmv_time": 0.0007305097579956058, 
        "phil_mean_time": 0.009396649830169678, 
        "phil_std_max_error": 0.012422435605970844, 
        "sigma": 0.12915496650148842
    }, 
    {
        "delta": 0.01, 
        "epsilon": 0.5646216173286173, 
        "matrix": "pathological_oski", 
        "matrix_domain": "Synthetic", 
        "matrix_m": 100000, 
        "matrix_n": 100000, 
        "matrix_name": "pathological_OSKI", 
        "matrix_nnz": 699994, 
        "matrix_size": 6922298, 
        "normal_spmv_time": 0.0011512398719787597, 
        "oski_mean_max_error": 3.6617525699548601, 
        "oski_mean_spmv_time": 0.00073079714775085554, 
        "oski_mean_time": 0.15315782920547485, 
        "oski_std_max_error": 0.034389802348876397, 
        "phil_mean_max_error": 0.017343411592672522, 
        "phil_mean_spmv_time": 0.0007305097579956058, 
        "phil_mean_time": 0.014227778968963623, 
        "phil_std_max_error": 0.010004073796979275, 
        "sigma": 0.2154434690031884
    }, 
    {
        "delta": 0.01, 
        "epsilon": 0.45731146138754825, 
        "matrix": "pathological_oski", 
        "matrix_domain": "Synthetic", 
        "matrix_m": 100000, 
        "matrix_n": 100000, 
        "matrix_name": "pathological_OSKI", 
        "matrix_nnz": 699994, 
        "matrix_size": 6922298, 
        "normal_spmv_time": 0.0011512398719787597, 
        "oski_mean_max_error": 3.6144437309757085, 
        "oski_mean_spmv_time": 0.00073075509071350217, 
        "oski_mean_time": 0.24540316060638429, 
        "oski_std_max_error": 0.13143067974120662, 
        "phil_mean_max_error": 0.014374989960500515, 
        "phil_mean_spmv_time": 0.0007305097579956058, 
        "phil_mean_time": 0.02160238021972656, 
        "phil_std_max_error": 0.0095020701869187076, 
        "sigma": 0.3593813663804628
    }, 
    {
        "delta": 0.01, 
        "epsilon": 0.37039632613764484, 
        "matrix": "pathological_oski", 
        "matrix_domain": "Synthetic", 
        "matrix_m": 100000, 
        "matrix_n": 100000, 
        "matrix_name": "pathological_OSKI", 
        "matrix_nnz": 699994, 
        "matrix_size": 6922298, 
        "normal_spmv_time": 0.0011512398719787597, 
        "oski_mean_max_error": 3.4348633378391922, 
        "oski_mean_spmv_time": 0.00073064994812011789, 
        "oski_mean_time": 0.4019415097238159, 
        "oski_std_max_error": 0.29328409512985576, 
        "phil_mean_max_error": 0.012130830846207707, 
        "phil_mean_spmv_time": 0.0007305097579956058, 
        "phil_mean_time": 0.032789880479431155, 
        "phil_std_max_error": 0.0064341712207167823, 
        "sigma": 0.5994842503189411
    }, 
    {
        "delta": 0.01, 
        "epsilon": 0.30000000000000016, 
        "matrix": "pathological_oski", 
        "matrix_domain": "Synthetic", 
        "matrix_m": 100000, 
        "matrix_n": 100000, 
        "matrix_name": "pathological_OSKI", 
        "matrix_nnz": 699994, 
        "matrix_size": 6922298, 
        "normal_spmv_time": 0.0011512398719787597, 
        "oski_mean_max_error": 5.4284775530856416e-05, 
        "oski_mean_spmv_time": 0.0007305097579956058, 
        "oski_mean_time": 0.6803185406578064, 
        "oski_std_max_error": 7.453889935837843e-20, 
        "phil_mean_max_error": 0.0097998659508896392, 
        "phil_mean_spmv_time": 0.0007305097579956058, 
        "phil_mean_time": 0.04963419894668579, 
        "phil_std_max_error": 0.0055296037760168828, 
        "sigma": 1.0000000000000002
    }
]